free_energy_landscape/freeEnergyLandscape.py
free_energy_landscape-1.0.3.dist-info/COPYING.LESSER
free_energy_landscape-1.0.3.dist-info/METADATA
free_energy_landscape-1.0.3.dist-info/WHEEL
free_energy_landscape-1.0.3.dist-info/entry_points.txt
free_energy_landscape-1.0.3.dist-info/top_level.txt
free_energy_landscape-1.0.3.dist-info/RECORD
