Metadata-Version: 2.1
Name: free_energy_landscape
Version: 1.0.3
Summary: The Free Energy Landscape Analysis tool provides a full suite for analyzing and visualizing free energy landscapes from molecular dynamics simulations. It focuses on deriving key insights from collective variable (CV) data, helping researchers deeply understand molecular systems' energetics and dynamics.
Author-email: Leon Sulfierry <sulfierry@gmail.com>
License: LGPL-3.0-only
Project-URL: Repository, https://github.com/sulfierry/free_energy_landscape/
Keywords: Free energy landscape,Molecular Dynamics,Collective variables,Boltzmann equation
Classifier: License :: OSI Approved :: GNU Lesser General Public License v3 (LGPLv3)
Classifier: Programming Language :: Python
Classifier: Programming Language :: Python :: 3
Classifier: Environment :: GPU
Classifier: Topic :: Scientific/Engineering
Classifier: Topic :: Scientific/Engineering :: Chemistry
Classifier: Topic :: Scientific/Engineering :: Bio-Informatics
Classifier: Topic :: Scientific/Engineering :: Physics
Requires-Python: >=3.8
License-File: COPYING.LESSER
Requires-Dist: numpy <2.0.0,>=1.23.5
Requires-Dist: imageio <3.0.0,>=2.34.0
Requires-Dist: matplotlib <4.0.0,>=3.7.4
Requires-Dist: scipy <2.0.0,==1.10.1
Requires-Dist: joblib <2.0.0,==1.3.2
